acryl/__init__.py
acryl/__main__.py
acryl/executor/__init__.py
acryl/executor/cloud_utils/__init__.py
acryl/executor/cloud_utils/cloud_copier.py
acryl/executor/cloud_utils/cloud_copier_location.py
acryl/executor/cloud_utils/env_utils.py
acryl/executor/cloud_utils/executor_credentials.py
acryl/executor/cloud_utils/s3_cloud_copier.py
acryl/executor/common/__init__.py
acryl/executor/common/config.py
acryl/executor/context/__init__.py
acryl/executor/context/execution_context.py
acryl/executor/context/executor_context.py
acryl/executor/dispatcher/__init__.py
acryl/executor/dispatcher/default_dispatcher.py
acryl/executor/dispatcher/dispatcher.py
acryl/executor/execution/__init__.py
acryl/executor/execution/default_executor.py
acryl/executor/execution/executor.py
acryl/executor/execution/ignore_executor.py
acryl/executor/execution/in_mem_ingestion_task.py
acryl/executor/execution/reporting_executor.py
acryl/executor/execution/runner.py
acryl/executor/execution/sub_process_ingestion_task.py
acryl/executor/execution/sub_process_task_common.py
acryl/executor/execution/sub_process_test_connection_task.py
acryl/executor/execution/task.py
acryl/executor/execution/task_registry.py
acryl/executor/execution/venv_utils.py
acryl/executor/report/__init__.py
acryl/executor/report/execution_report.py
acryl/executor/request/__init__.py
acryl/executor/request/execution_request.py
acryl/executor/request/signal_request.py
acryl/executor/result/__init__.py
acryl/executor/result/execution_result.py
acryl/executor/secret/__init__.py
acryl/executor/secret/datahub_secret_store.py
acryl/executor/secret/datahub_secrets_client.py
acryl/executor/secret/environment_secret_store.py
acryl/executor/secret/file_secret_store.py
acryl/executor/secret/secret_store.py
acryl/executor/secret/secret_store_registry.py
acryl_executor-0.2.9.data/scripts/install_acryl_datahub.sh
acryl_executor-0.2.9.data/scripts/run_ingest.sh
acryl_executor-0.2.9.data/scripts/run_test_connection.sh
acryl_executor-0.2.9.dist-info/licenses/LICENSE
acryl_executor-0.2.9.dist-info/METADATA
acryl_executor-0.2.9.dist-info/WHEEL
acryl_executor-0.2.9.dist-info/entry_points.txt
acryl_executor-0.2.9.dist-info/top_level.txt
acryl_executor-0.2.9.dist-info/RECORD
